edgetpu_compiler_log_parser/__init__.py
edgetpu_compiler_log_parser/edgetpu_compiler_log_parser.py
edgetpu_compiler_log_parser-0.1.6.dist-info/licenses/LICENSE
edgetpu_compiler_log_parser-0.1.6.dist-info/METADATA
edgetpu_compiler_log_parser-0.1.6.dist-info/WHEEL
edgetpu_compiler_log_parser-0.1.6.dist-info/top_level.txt
edgetpu_compiler_log_parser-0.1.6.dist-info/RECORD
