Metadata-Version: 2.4
Name: edgetpu_compiler_log_parser
Version: 0.1.6
Summary: Parse EdgeTPU compiler log
Author-email: Changhun Han <ehwjs1914@naver.com>
License: MIT License
Project-URL: Homepage, https://github.com/HanChangHun/edgetpu-compiler-log-parser
Project-URL: Repository, https://github.com/HanChangHun/edgetpu-compiler-log-parser
Project-URL: Issues, https://github.com/HanChangHun/edgetpu-compiler-log-parser/issues
Keywords: EdgeTPU,compiler,log,parser
Classifier: Programming Language :: Python :: 3
Classifier: Operating System :: OS Independent
Classifier: License :: OSI Approved :: MIT License
Requires-Python: >=3.7
License-File: LICENSE
Requires-Dist: build>=1.1.1
Requires-Dist: twine>=4.0.2
Dynamic: license-file
